searchrepo.py
searchgithubrepo-1.0.10.dist-info/LICENSE
searchgithubrepo-1.0.10.dist-info/METADATA
searchgithubrepo-1.0.10.dist-info/WHEEL
searchgithubrepo-1.0.10.dist-info/top_level.txt
searchgithubrepo-1.0.10.dist-info/RECORD
