Metadata-Version: 2.1
Name: searchgithubrepo
Version: 1.0.10
Summary: Search repositories on GitHub
Home-page: https://github.com/tushartushar/search-repo
Author: Tushar Sharma
Author-email: 000.tushar@gmail.com
License: Apache License
Platform: UNKNOWN
Classifier: Development Status :: 5 - Production/Stable
Classifier: Environment :: Console
Classifier: Intended Audience :: Developers
Classifier: Intended Audience :: Science/Research
Classifier: License :: OSI Approved :: Apache Software License
Classifier: Programming Language :: Python :: 3.7
Classifier: Programming Language :: Python :: 3.8
Classifier: Programming Language :: Python :: 3.9
Classifier: Topic :: Software Development :: Libraries :: Python Modules
Classifier: Operating System :: OS Independent
Classifier: Operating System :: POSIX
Classifier: Operating System :: Microsoft :: Windows
Classifier: Operating System :: MacOS :: MacOS X
Requires-Python: >=3.7
License-File: LICENSE
Requires-Dist: certifi (==2022.6.15)
Requires-Dist: charset-normalizer (==2.1.0)
Requires-Dist: idna (==3.3)
Requires-Dist: requests (==2.28.1)
Requires-Dist: urllib3 (==1.26.11)
